farapayamak/__init__.py
farapayamak/rest.py
farapayamak/soap.py
farapayamak-1.2.0.dist-info/LICENSE
farapayamak-1.2.0.dist-info/METADATA
farapayamak-1.2.0.dist-info/WHEEL
farapayamak-1.2.0.dist-info/top_level.txt
farapayamak-1.2.0.dist-info/RECORD
