Metadata-Version: 2.1
Name: farapayamak
Version: 1.2.0
Summary: Farapayamak REST and SOAP Webservice Wrapper (SDK)
Home-page: https://github.com/farapayamak/python
Author: Amirhossein Mehrvarzi
Author-email: farapayamakdev@gmail.com
Project-URL: Bug Tracker, https://github.com/farapayamak/python/issues
Classifier: Programming Language :: Python :: 3
Classifier: License :: OSI Approved :: MIT License
Classifier: Operating System :: OS Independent
Requires-Python: >=3.6
License-File: LICENSE
